sdo_citations-0.0.1.data/scripts/sdo-citations
standardcitations/__init__.py
standardcitations/standardcitations.py
sdo_citations-0.0.1.dist-info/METADATA
sdo_citations-0.0.1.dist-info/WHEEL
sdo_citations-0.0.1.dist-info/top_level.txt
sdo_citations-0.0.1.dist-info/RECORD
