Metadata-Version: 2.1
Name: sdo-citations
Version: 0.0.1
Summary: This project generates BiBTeX-files for 3GPP specifications. Its a fork from martisak/3gpp-citations from Github
Home-page: https://github.com/kspviswa/3gpp-citations
Author: Viswa Kumar
Author-email: kspviswaphd@gmail.com
License: MIT
Platform: any
Classifier: Environment :: Console
Classifier: Intended Audience :: Science/Research
Classifier: Topic :: Education
Classifier: License :: OSI Approved :: MIT License
Classifier: Operating System :: OS Independent
Classifier: Natural Language :: English
Requires-Python: >=3
Requires-Dist: bibtexparser ==1.4.1
Requires-Dist: certifi ==2023.7.22
Requires-Dist: charset-normalizer ==3.3.1
Requires-Dist: et-xmlfile ==1.1.0
Requires-Dist: idna ==3.4
Requires-Dist: jdcal ==1.4.1
Requires-Dist: lxml ==4.9.3
Requires-Dist: openpyxl ==2.4.8
Requires-Dist: pyparsing ==3.1.1
Requires-Dist: requests ==2.31.0
Requires-Dist: tqdm ==4.66.1
Requires-Dist: urllib3 ==2.0.7
